README.rst
setup.py
gpsd/__init__.py
gpsd_py3.egg-info/PKG-INFO
gpsd_py3.egg-info/SOURCES.txt
gpsd_py3.egg-info/dependency_links.txt
gpsd_py3.egg-info/top_level.txt