Metadata-Version: 1.1
Name: gpsd-py3
Version: 0.3.0
Summary: Python 3 library for working with gpsd
Home-page: https://github.com/MartijnBraam/gpsd-py3
Author: Martijn Braam
Author-email: martijn@brixit.nl
License: MIT
Keywords: gps,gpsd
Platform: UNKNOWN
Classifier: Programming Language :: Python
Classifier: Programming Language :: Python :: 3
Classifier: Development Status :: 4 - Beta
Classifier: Operating System :: POSIX :: Linux
Classifier: License :: OSI Approved :: MIT License
